poppy_4dof_arm_mini
