Metadata-Version: 1.0
Name: poppy-4dof-arm-mini
Version: 1.0.1
Summary:  Poppy 4 dof arm mini Software Library
Home-page: https://github.com/poppy-project/poppy-4dof-arm-mini
Author: Pierre Rouanet, Jonathan Grizou, Matthieu Lapeyre
Author-email: pierre.rouanet@gmail.com
License: GNU GENERAL PUBLIC LICENSE Version 3
Platform: UNKNOWN
